chemical_QBD/__init__.py
chemical_QBD/const.py
chemical_QBD/elementary__data.json
chemical_QBD/tools.py
chemical_QBD-0.0.40.dist-info/LICENSE
chemical_QBD-0.0.40.dist-info/METADATA
chemical_QBD-0.0.40.dist-info/WHEEL
chemical_QBD-0.0.40.dist-info/top_level.txt
chemical_QBD-0.0.40.dist-info/RECORD
