Metadata-Version: 2.1
Name: chemical-QBD
Version: 0.0.40
Summary: Tools for chemical elements and compounds.
Home-page: https://github.com/QuantumBrainDisorder/chemical_QBD
Author: Rabarbar Batman
Author-email: 2rr@tuta.io
License: GPLv3
Project-URL: Source Code, https://github.com/QuantumBrainDisorder/chemical_QBD
Project-URL: Bug Tracker, https://github.com/QuantumBrainDisorder/chemical_QBD/issues
Keywords: chemistry,chemical elements,chemical compounds,material engineering
Platform: UNKNOWN
Classifier: Programming Language :: Python :: 3.9
Classifier: Topic :: Scientific/Engineering
Classifier: Topic :: Scientific/Engineering :: Chemistry
Classifier: Development Status :: 2 - Pre-Alpha
Classifier: License :: OSI Approved :: GNU General Public License v3 (GPLv3)
Classifier: Environment :: Console
Classifier: Intended Audience :: Science/Research
Classifier: Intended Audience :: Education
Classifier: Natural Language :: English
Requires-Python: >=3.9
